gittoolbox/__init__.py
gittoolbox/git/__init__.py
gittoolbox/git/git_repo.py
gittoolbox/heatmap/__init__.py
gittoolbox/heatmap/heatmap.py
gittoolbox/heatmap/heatmap_cli.py
gittoolbox-0.2.1.dist-info/LICENSE
gittoolbox-0.2.1.dist-info/METADATA
gittoolbox-0.2.1.dist-info/WHEEL
gittoolbox-0.2.1.dist-info/entry_points.txt
gittoolbox-0.2.1.dist-info/top_level.txt
gittoolbox-0.2.1.dist-info/RECORD
