Metadata-Version: 2.1
Name: gittoolbox
Version: 0.2.1
Summary: UNKNOWN
Home-page: https://github.com/dbradf/gittoolbox
Author: David Bradford
Author-email: david.bradford@mongodb.com
License: Apache License, Version 2.0
Platform: UNKNOWN
Classifier: Intended Audience :: Developers
Classifier: Operating System :: Unix
Classifier: Operating System :: POSIX
Classifier: Operating System :: Microsoft :: Windows
Classifier: Programming Language :: Python
Classifier: Programming Language :: Python :: 2
Classifier: Programming Language :: Python :: 3
Classifier: Programming Language :: Python :: Implementation :: CPython
Classifier: Programming Language :: Python :: Implementation :: PyPy
Requires-Dist: Click (~=7.0)
Requires-Dist: GitPython (~=2.1.11)
Requires-Dist: PyYAML (~=5.1)
Requires-Dist: requests (~=2.22.0)
Requires-Dist: structlog (~=19.1.0)
